README.md
pyproject.toml
setup.py
dataset_search/__init__.py
dataset_search/search.py
dataset_search_engine.egg-info/PKG-INFO
dataset_search_engine.egg-info/SOURCES.txt
dataset_search_engine.egg-info/dependency_links.txt
dataset_search_engine.egg-info/requires.txt
dataset_search_engine.egg-info/top_level.txt