Metadata-Version: 2.1
Name: dataset-search-engine
Version: 1.0.0
Summary: An AI-powered dataset search engine across Hugging Face, Kaggle, and Google Dataset Search
Home-page: https://github.com/arunm6832/dataset-search-engine
Author: Your Name
Author-email: your.email@example.com
Classifier: Programming Language :: Python :: 3
Classifier: License :: OSI Approved :: MIT License
Classifier: Operating System :: OS Independent
Requires-Python: >=3.7
